Workbook

Sheet Car True Cost
A1: Car-Payment True-Cost Calculator (yellow = your inputs)
A2: Educational only. Not financial advice. Figures are illustrations from your own inputs; no returns or savings are guaranteed.
A4: Vehicle price ($) | B4: 35000
A5: Down payment ($) | B5: 3000
A6: Trade-in value ($) | B6: 0
A7: Sales tax rate (%) | B7: 6
A8: Fees: title, registration, doc ($) | B8: 800
A9: Loan APR (%) | B9: 7.5
A10: Loan term (months) | B10: 72
A11: Insurance per month ($) | B11: 150
A12: Fuel/charging per month ($) | B12: 160
A13: Maintenance per month ($) | B13: 80
A14: Assumed annual return if invested instead (%) - your assumption | B14: 7
A15: Years to compare | B15: 30
A18: Amount financed ($) | B18: =B4+B4*B7/100+B8-B5-B6
A19: Monthly loan payment ($) | B19: =IF(B9=0,B18/B10,PMT(B9/100/12,B10,-B18))
A20: Total of loan payments ($) | B20: =B19*B10
A21: Total interest paid ($) | B21: =B20-B18
A22: All-in cost of the car over the loan ($) | B22: =B5+B6+B20
A23: Monthly cost to own incl. insurance, fuel, maintenance ($) | B23: =B19+B11+B12+B13
A24: Total cost to own over the loan term ($) | B24: =B23*B10
A25: If the loan payment were invested monthly for the loan term, value at end of term ($) | B25: =FV(B14/100/12,B10,-B19)
A26: ...then left to grow until 'Years to compare' ($) | B26: =B25*(1+B14/100/12)^MAX(0,B15*12-B10)
A27: If you repeat this car loan back-to-back for 'Years to compare', total payments ($) | B27: =B19*B15*12
A29: Formulas: PMT = standard amortizing loan payment; FV = monthly contributions compounded monthly at YOUR assumed rate. Real returns vary and can be negative.

Sheet Term Compare
A1: Same car, different loan terms (uses Car True Cost inputs)
A2: Educational only. Not financial advice. Figures are illustrations from your own inputs; no returns or savings are guaranteed.
A4: Term (months) | B4: Monthly payment | C4: Total paid | D4: Total interest
A5: 36 | B5: =IF('Car True Cost'!B9=0,'Car True Cost'!B18/A5,PMT('Car True Cost'!B9/100/12,A5,-'Car True Cost'!B18)) | C5: =B5*A5 | D5: =C5-'Car True Cost'!B18
A6: 48 | B6: =IF('Car True Cost'!B9=0,'Car True Cost'!B18/A6,PMT('Car True Cost'!B9/100/12,A6,-'Car True Cost'!B18)) | C6: =B6*A6 | D6: =C6-'Car True Cost'!B18
A7: 60 | B7: =IF('Car True Cost'!B9=0,'Car True Cost'!B18/A7,PMT('Car True Cost'!B9/100/12,A7,-'Car True Cost'!B18)) | C7: =B7*A7 | D7: =C7-'Car True Cost'!B18
A8: 72 | B8: =IF('Car True Cost'!B9=0,'Car True Cost'!B18/A8,PMT('Car True Cost'!B9/100/12,A8,-'Car True Cost'!B18)) | C8: =B8*A8 | D8: =C8-'Car True Cost'!B18
A9: 84 | B9: =IF('Car True Cost'!B9=0,'Car True Cost'!B18/A9,PMT('Car True Cost'!B9/100/12,A9,-'Car True Cost'!B18)) | C9: =B9*A9 | D9: =C9-'Car True Cost'!B18

Sheet Price Check
A1: Personal Inflation Price Check: compare your own statements
A2: Educational only. Not financial advice. Figures are illustrations from your own inputs; no returns or savings are guaranteed.
A4: Item | B4: Price 12 months ago | C4: Price now | D4: % change | E4: Times bought per month | F4: Extra cost per month
A5: Groceries (weekly trip) | D5: =IF(B5>0,(C5-B5)/B5,"") | F5: =(C5-B5)*E5
A6: Eggs (dozen) | D6: =IF(B6>0,(C6-B6)/B6,"") | F6: =(C6-B6)*E6
A7: Ground beef (lb) | D7: =IF(B7>0,(C7-B7)/B7,"") | F7: =(C7-B7)*E7
A8: Eating out (meal) | D8: =IF(B8>0,(C8-B8)/B8,"") | F8: =(C8-B8)*E8
A9: Electricity bill | D9: =IF(B9>0,(C9-B9)/B9,"") | F9: =(C9-B9)*E9
A10: Gasoline (gallon) | D10: =IF(B10>0,(C10-B10)/B10,"") | F10: =(C10-B10)*E10
A11: Rent / mortgage | D11: =IF(B11>0,(C11-B11)/B11,"") | F11: =(C11-B11)*E11
A12: Car insurance | D12: =IF(B12>0,(C12-B12)/B12,"") | F12: =(C12-B12)*E12
A13: Phone / internet | D13: =IF(B13>0,(C13-B13)/B13,"") | F13: =(C13-B13)*E13
A14: Other | D14: =IF(B14>0,(C14-B14)/B14,"") | F14: =(C14-B14)*E14
A16: Total extra per month | F16: =SUM(F5:F14)
A17: Total extra per year | F17: =F16*12
A19: Personal weighted inflation (this list) | F19: =IF(SUMPRODUCT(B5:B14,E5:E14)>0,SUMPRODUCT(C5:C14,E5:E14)/SUMPRODUCT(B5:B14,E5:E14)-1,"")

Sheet Monthly Budget
A1: Monthly Budget: plan vs actual
A2: Educational only. Not financial advice. Figures are illustrations from your own inputs; no returns or savings are guaranteed.
A4: Take-home income this month ($)
A6: Category | B6: Planned | C6: Actual | D6: Difference (Planned - Actual)
A7: Housing | D7: =B7-C7
A8: Utilities | D8: =B8-C8
A9: Groceries | D9: =B9-C9
A10: Transportation (car payment, fuel, insurance) | D10: =B10-C10
A11: Debt payments | D11: =B11-C11
A12: Savings / emergency fund | D12: =B12-C12
A13: Retirement | D13: =B13-C13
A14: Insurance (health, life) | D14: =B14-C14
A15: Phone / internet | D15: =B15-C15
A16: Subscriptions | D16: =B16-C16
A17: Eating out / fun | D17: =B17-C17
A18: Giving | D18: =B18-C18
A19: Other | D19: =B19-C19
A20: Totals | B20: =SUM(B7:B19) | C20: =SUM(C7:C19) | D20: =SUM(D7:D19)
A21: Left over after planned spending | B21: =B4-B20
A22: Left over after actual spending | C22: =B4-C20
